{
  "id": "19",
  "title": "GraphQL types package exports",
  "description": "Update `app/graphql/types/__init__.py` to re-export all GraphQL types: UserType, SkillType, ProjectType, CollaboratorType, TribeType, TribeMemberType, OpenRoleType, FeedEventType.",
  "acceptance_criteria": "- All types imported and re-exported\n- __all__ list defined\n- Types can be imported from graphql.types package",
  "depends_on": [
    "15",
    "16",
    "17",
    "18"
  ],
  "status": "pending",
  "branch": "tribe/task-19-graphql-types-package-exports",
  "agent_model": "sonnet",
  "created_at": "2026-02-10T23:07:31Z",
  "started_at": null,
  "completed_at": null,
  "agent_pid": null,
  "error": null,
  "review_feedback": null
}
